LICENSE
prungo/__init__.py
prungo/constants.py
prungo/decorators.py
prungo/interfaces.py
prungo/models.py
prungo/utils.py
prungo-1.0.7.dist-info/LICENSE
prungo-1.0.7.dist-info/METADATA
prungo-1.0.7.dist-info/WHEEL
prungo-1.0.7.dist-info/RECORD
