Metadata-Version: 2.1
Name: prungo
Version: 1.0.7
Summary: A package for basic utility functions/classes
Home-page: https://github.com/c-prungo/prungo-util
License: MIT
Author: c-prungo
Requires-Python: >=3.10,<4.0
Classifier: License :: OSI Approved :: MIT License
Classifier: Operating System :: OS Independent
Classifier: Programming Language :: Python :: 3
Classifier: Programming Language :: Python :: 3.10
Classifier: Programming Language :: Python :: 3.11
Requires-Dist: pydantic (>=1.10.8,<2.0.0)
Project-URL: Repository, https://github.com/c-prungo/prungo-util
